pyavrdebug/__init__.py
pyavrdebug/version.py
pyavrdebug-0.0.0.1.dist-info/LICENSE.txt
pyavrdebug-0.0.0.1.dist-info/METADATA
pyavrdebug-0.0.0.1.dist-info/WHEEL
pyavrdebug-0.0.0.1.dist-info/top_level.txt
pyavrdebug-0.0.0.1.dist-info/RECORD
